{"efVersion":"0.8.5.0","efModuleName":["Data","CatList"],"efExports":[{"TypeRef":["CatList",["CatNil","CatCons"]]},{"ValueRef":{"Ident":"uncons"}},{"ValueRef":{"Ident":"snoc"}},{"ValueRef":{"Ident":"cons"}},{"ValueRef":{"Ident":"append"}},{"ValueRef":{"Ident":"null"}},{"ValueRef":{"Ident":"empty"}},{"TypeInstanceRef":{"Ident":"semigroupCatList"}},{"TypeInstanceRef":{"Ident":"monoidCatList"}},{"TypeInstanceRef":{"Ident":"showCatList"}}],"efImports":[{"eiModule":["Prim"],"eiImportType":{"Implicit":[]},"eiImportedAs":null},{"eiModule":["Prelude"],"eiImportType":{"Explicit":[{"PositionedDeclarationRef":[{"start":[19,17],"name":"/Users/rocaboca/projects/checkmate/bower_components/purescript-catenable-lists/src/Data/CatList.purs","end":[19,26]},[],{"TypeClassRef":"Semigroup"}]},{"PositionedDeclarationRef":[{"start":[19,28],"name":"/Users/rocaboca/projects/checkmate/bower_components/purescript-catenable-lists/src/Data/CatList.purs","end":[19,32]},[],{"TypeClassRef":"Show"}]},{"PositionedDeclarationRef":[{"start":[19,34],"name":"/Users/rocaboca/projects/checkmate/bower_components/purescript-catenable-lists/src/Data/CatList.purs","end":[19,38]},[],{"ValueRef":{"Op":"++"}}]},{"PositionedDeclarationRef":[{"start":[19,40],"name":"/Users/rocaboca/projects/checkmate/bower_components/purescript-catenable-lists/src/Data/CatList.purs","end":[19,44]},[],{"ValueRef":{"Ident":"show"}}]}]},"eiImportedAs":null},{"eiModule":["Data","Maybe"],"eiImportType":{"Explicit":[{"PositionedDeclarationRef":[{"start":[21,20],"name":"/Users/rocaboca/projects/checkmate/bower_components/purescript-catenable-lists/src/Data/CatList.purs","end":[21,29]},[],{"TypeRef":["Maybe",null]}]}]},"eiImportedAs":null},{"eiModule":["Data","Monoid"],"eiImportType":{"Explicit":[{"PositionedDeclarationRef":[{"start":[22,21],"name":"/Users/rocaboca/projects/checkmate/bower_components/purescript-catenable-lists/src/Data/CatList.purs","end":[22,27]},[],{"TypeClassRef":"Monoid"}]}]},"eiImportedAs":null},{"eiModule":["Data","Tuple"],"eiImportType":{"Explicit":[{"PositionedDeclarationRef":[{"start":[23,20],"name":"/Users/rocaboca/projects/checkmate/bower_components/purescript-catenable-lists/src/Data/CatList.purs","end":[23,29]},[],{"TypeRef":["Tuple",null]}]}]},"eiImportedAs":null},{"eiModule":["Data","CatQueue"],"eiImportType":{"Implicit":[]},"eiImportedAs":["Q"]},{"eiModule":["Data","List"],"eiImportType":{"Implicit":[]},"eiImportedAs":["L"]}],"efFixities":[],"efDeclarations":[{"EDType":{"edTypeName":"CatList","edTypeKind":{"tag":"FunKind","contents":[{"tag":"Star","contents":[]},{"tag":"Star","contents":[]}]},"edTypeDeclarationKind":{"DataType":[[["a",{"tag":"Star","contents":[]}]],[["CatNil",[]],["CatCons",[{"tag":"TypeVar","contents":"a"},{"tag":"TypeApp","contents":[{"tag":"TypeConstructor","contents":[["Data","CatQueue"],"CatQueue"]},{"tag":"TypeApp","contents":[{"tag":"TypeConstructor","contents":[["Data","CatList"],"CatList"]},{"tag":"TypeVar","contents":"a"}]}]}]]]]}}},{"EDDataConstructor":{"edDataCtorName":"CatNil","edDataCtorOrigin":"data","edDataCtorTypeCtor":"CatList","edDataCtorType":{"tag":"ForAll","contents":["a",{"tag":"TypeApp","contents":[{"tag":"TypeConstructor","contents":[["Data","CatList"],"CatList"]},{"tag":"TypeVar","contents":"a"}]},null]},"edDataCtorFields":[]}},{"EDDataConstructor":{"edDataCtorName":"CatCons","edDataCtorOrigin":"data","edDataCtorTypeCtor":"CatList","edDataCtorType":{"tag":"ForAll","contents":["a",{"tag":"TypeApp","contents":[{"tag":"TypeApp","contents":[{"tag":"TypeConstructor","contents":[["Prim"],"Function"]},{"tag":"TypeVar","contents":"a"}]},{"tag":"TypeApp","contents":[{"tag":"TypeApp","contents":[{"tag":"TypeConstructor","contents":[["Prim"],"Function"]},{"tag":"TypeApp","contents":[{"tag":"TypeConstructor","contents":[["Data","CatQueue"],"CatQueue"]},{"tag":"TypeApp","contents":[{"tag":"TypeConstructor","contents":[["Data","CatList"],"CatList"]},{"tag":"TypeVar","contents":"a"}]}]}]},{"tag":"TypeApp","contents":[{"tag":"TypeConstructor","contents":[["Data","CatList"],"CatList"]},{"tag":"TypeVar","contents":"a"}]}]}]},null]},"edDataCtorFields":[{"Ident":"value0"},{"Ident":"value1"}]}},{"EDValue":{"edValueName":{"Ident":"uncons"},"edValueType":{"tag":"ForAll","contents":["a",{"tag":"TypeApp","contents":[{"tag":"TypeApp","contents":[{"tag":"TypeConstructor","contents":[["Prim"],"Function"]},{"tag":"TypeApp","contents":[{"tag":"TypeConstructor","contents":[["Data","CatList"],"CatList"]},{"tag":"TypeVar","contents":"a"}]}]},{"tag":"TypeApp","contents":[{"tag":"TypeConstructor","contents":[["Data","Maybe"],"Maybe"]},{"tag":"TypeApp","contents":[{"tag":"TypeApp","contents":[{"tag":"TypeConstructor","contents":[["Data","Tuple"],"Tuple"]},{"tag":"TypeVar","contents":"a"}]},{"tag":"TypeApp","contents":[{"tag":"TypeConstructor","contents":[["Data","CatList"],"CatList"]},{"tag":"TypeVar","contents":"a"}]}]}]}]},20]}}},{"EDValue":{"edValueName":{"Ident":"snoc"},"edValueType":{"tag":"ForAll","contents":["a",{"tag":"TypeApp","contents":[{"tag":"TypeApp","contents":[{"tag":"TypeConstructor","contents":[["Prim"],"Function"]},{"tag":"TypeApp","contents":[{"tag":"TypeConstructor","contents":[["Data","CatList"],"CatList"]},{"tag":"TypeVar","contents":"a"}]}]},{"tag":"TypeApp","contents":[{"tag":"TypeApp","contents":[{"tag":"TypeConstructor","contents":[["Prim"],"Function"]},{"tag":"TypeVar","contents":"a"}]},{"tag":"TypeApp","contents":[{"tag":"TypeConstructor","contents":[["Data","CatList"],"CatList"]},{"tag":"TypeVar","contents":"a"}]}]}]},33]}}},{"EDValue":{"edValueName":{"Ident":"cons"},"edValueType":{"tag":"ForAll","contents":["a",{"tag":"TypeApp","contents":[{"tag":"TypeApp","contents":[{"tag":"TypeConstructor","contents":[["Prim"],"Function"]},{"tag":"TypeVar","contents":"a"}]},{"tag":"TypeApp","contents":[{"tag":"TypeApp","contents":[{"tag":"TypeConstructor","contents":[["Prim"],"Function"]},{"tag":"TypeApp","contents":[{"tag":"TypeConstructor","contents":[["Data","CatList"],"CatList"]},{"tag":"TypeVar","contents":"a"}]}]},{"tag":"TypeApp","contents":[{"tag":"TypeConstructor","contents":[["Data","CatList"],"CatList"]},{"tag":"TypeVar","contents":"a"}]}]}]},29]}}},{"EDValue":{"edValueName":{"Ident":"append"},"edValueType":{"tag":"ForAll","contents":["a",{"tag":"TypeApp","contents":[{"tag":"TypeApp","contents":[{"tag":"TypeConstructor","contents":[["Prim"],"Function"]},{"tag":"TypeApp","contents":[{"tag":"TypeConstructor","contents":[["Data","CatList"],"CatList"]},{"tag":"TypeVar","contents":"a"}]}]},{"tag":"TypeApp","contents":[{"tag":"TypeApp","contents":[{"tag":"TypeConstructor","contents":[["Prim"],"Function"]},{"tag":"TypeApp","contents":[{"tag":"TypeConstructor","contents":[["Data","CatList"],"CatList"]},{"tag":"TypeVar","contents":"a"}]}]},{"tag":"TypeApp","contents":[{"tag":"TypeConstructor","contents":[["Data","CatList"],"CatList"]},{"tag":"TypeVar","contents":"a"}]}]}]},27]}}},{"EDValue":{"edValueName":{"Ident":"null"},"edValueType":{"tag":"ForAll","contents":["a",{"tag":"TypeApp","contents":[{"tag":"TypeApp","contents":[{"tag":"TypeConstructor","contents":[["Prim"],"Function"]},{"tag":"TypeApp","contents":[{"tag":"TypeConstructor","contents":[["Data","CatList"],"CatList"]},{"tag":"TypeVar","contents":"a"}]}]},{"tag":"TypeConstructor","contents":[["Prim"],"Boolean"]}]},2]}}},{"EDValue":{"edValueName":{"Ident":"empty"},"edValueType":{"tag":"ForAll","contents":["a",{"tag":"TypeApp","contents":[{"tag":"TypeConstructor","contents":[["Data","CatList"],"CatList"]},{"tag":"TypeVar","contents":"a"}]},24]}}},{"EDInstance":{"edInstanceClassName":[["Prelude"],"Semigroup"],"edInstanceName":{"Ident":"semigroupCatList"},"edInstanceTypes":[{"tag":"TypeApp","contents":[{"tag":"TypeConstructor","contents":[["Data","CatList"],"CatList"]},{"tag":"TypeVar","contents":"a"}]}],"edInstanceConstraints":[]}},{"EDInstance":{"edInstanceClassName":[["Data","Monoid"],"Monoid"],"edInstanceName":{"Ident":"monoidCatList"},"edInstanceTypes":[{"tag":"TypeApp","contents":[{"tag":"TypeConstructor","contents":[["Data","CatList"],"CatList"]},{"tag":"TypeVar","contents":"a"}]}],"edInstanceConstraints":[]}},{"EDInstance":{"edInstanceClassName":[["Prelude"],"Show"],"edInstanceName":{"Ident":"showCatList"},"edInstanceTypes":[{"tag":"TypeApp","contents":[{"tag":"TypeConstructor","contents":[["Data","CatList"],"CatList"]},{"tag":"TypeVar","contents":"a"}]}],"edInstanceConstraints":[[[["Prelude"],"Show"],[{"tag":"TypeVar","contents":"a"}]]]}}]}